hebe_api/__init__.py
hebe_api/simple.py
hebe_api-3.0.0.dist-info/METADATA
hebe_api-3.0.0.dist-info/WHEEL
hebe_api-3.0.0.dist-info/top_level.txt
hebe_api-3.0.0.dist-info/RECORD
